LICENCE.txt
README.md
setup.cfg
setup.py
cnrtncy_library_globalaihub.egg-info/PKG-INFO
cnrtncy_library_globalaihub.egg-info/SOURCES.txt
cnrtncy_library_globalaihub.egg-info/dependency_links.txt
cnrtncy_library_globalaihub.egg-info/entry_points.txt
cnrtncy_library_globalaihub.egg-info/requires.txt
cnrtncy_library_globalaihub.egg-info/top_level.txt
library/__init__.py
library/app.py
library/app_entry.py
library/logger.py